csv_to_snowflake/__init__.py
csv_to_snowflake/main.py
csv_to_snowflake-0.2.1.dist-info/entry_points.txt
csv_to_snowflake-0.2.1.dist-info/WHEEL
csv_to_snowflake-0.2.1.dist-info/METADATA
csv_to_snowflake-0.2.1.dist-info/RECORD
